embed_wrapper/__init__.py
embed_wrapper/helpers.py
embed_wrapper/wrapper.py
discord.py_embed_wrapper-0.0.9.dist-info/LICENSE
discord.py_embed_wrapper-0.0.9.dist-info/METADATA
discord.py_embed_wrapper-0.0.9.dist-info/WHEEL
discord.py_embed_wrapper-0.0.9.dist-info/top_level.txt
discord.py_embed_wrapper-0.0.9.dist-info/RECORD
