Metadata-Version: 2.1
Name: discord.py-embed-wrapper
Version: 0.0.9
Summary: A small wrapper for easy creation of discord.py Embeds and sending/editing of Messages including those Embeds
Home-page: https://gitlab.com/sleoh/discord.py-embed-wrapper
Author: sleoh
Author-email: simon.henkel@gmx.de
License: UNKNOWN
Platform: UNKNOWN
Classifier: Programming Language :: Python :: 3
Classifier: License :: OSI Approved :: MIT License
Classifier: Operating System :: OS Independent
Requires-Python: >=3.6
